hochiminh/__init__.py
hochiminh/pdf_parser.py
hochiminh/dev/__init__.py
hochiminh/dev/cell_detector_simple.py
hochiminh/dev/font_to_image.py
hochiminh/dev/keras_filtering.py
hochiminh/dev/keras_test.py
hochiminh/dev/main.so.py
hochiminh/dev/to_csv.py
hochiminh/image_processing/__init__.py
hochiminh/image_processing/connected_components.py
hochiminh/image_processing/cross_detector.py
hochiminh/image_processing/geometry.py
hochiminh/image_processing/hochiminh.py
hochiminh/image_processing/lines_detector.py
hochiminh/image_processing/ocr.py
hochiminh/io/__init__.py
hochiminh/io/pdfconverter.py
hochiminh/io/reader.py
HoChiMinh-1.0.0.dist-info/METADATA
HoChiMinh-1.0.0.dist-info/WHEEL
HoChiMinh-1.0.0.dist-info/top_level.txt
HoChiMinh-1.0.0.dist-info/RECORD
