Metadata-Version: 2.1
Name: HoChiMinh
Version: 1.0.0
Summary: Ho Chi Minh is designed to extract textual information from tables presented in PDF, pictures or other format. Хошимин предназначен для извлечения текстовой информации из таблиц, представленных в PDF, картинках или ином формате.
Home-page: https://github.com/Hedgehogues/HoChiMinh
Author: Egor Urvanov
Author-email: hedgehogues@bk.ru
License: UNKNOWN
Platform: UNKNOWN
Classifier: Programming Language :: Python :: 3.7
Classifier: Operating System :: OS Independent
Requires-Dist: opencv-python (==3.4.2.17)
Requires-Dist: scikit-learn (==0.21.0)
Requires-Dist: scikit-image (==0.16.2)
Requires-Dist: pytesseract (==0.2.0)
Requires-Dist: scipy (==1.3.1)
Requires-Dist: pdf2image (==0.1.9)
Requires-Dist: xlrd (==1.1.0)
Requires-Dist: pillow (==5.2.0)
